mac_youtube/__init__.py
mac_youtube/download.py
mac_youtube/pause.py
mac_youtube/play.py
mac_youtube/playing.py
mac_youtube/urls.py
mac_youtube-2019.3.27.dist-info/METADATA
mac_youtube-2019.3.27.dist-info/WHEEL
mac_youtube-2019.3.27.dist-info/top_level.txt
mac_youtube-2019.3.27.dist-info/RECORD
