Metadata-Version: 2.1
Name: mac-youtube
Version: 2019.3.27
Summary: MacOS youtube download, Google Chrome.app play/pause
Home-page: https://github.com/looking-for-a-job/mac-youtube.py
License: UNKNOWN
Keywords: youtube
Platform: UNKNOWN
Classifier: License :: Public Domain
Classifier: Operating System :: MacOS
Classifier: Programming Language :: Python
Classifier: Programming Language :: Python :: 2
Classifier: Programming Language :: Python :: 2.7
Classifier: Programming Language :: Python :: 3
Classifier: Programming Language :: Python :: 3.4
Classifier: Programming Language :: Python :: 3.5
Classifier: Programming Language :: Python :: 3.6
Classifier: Programming Language :: Python :: 3.7
Classifier: Topic :: Software Development
Requires-Dist: applescript
Requires-Dist: click
Requires-Dist: google-chrome
Requires-Dist: public
Requires-Dist: setuptools
Requires-Dist: youtube-dl
